{
    "themes": [
        {
            "theme_name": "Olympic",
            "theme_thumbnail": "theme_olympic_3/background.png",
            "theme_url": "theme_olympic_3"
        },
        {
            "theme_name": "Christmas",
            "theme_thumbnail": "theme_christmas/background.png",
            "theme_url": "theme_christmas"
        },
        {
            "theme_name": "Khmer Art",
            "theme_thumbnail": "theme_khmer_3/background.png",
            "theme_url": "theme_khmer_3"
        },
        {
            "theme_name": "Animal",
            "theme_thumbnail": "theme_animal_3/background.png",
            "theme_url": "theme_animal_3"
        }
    ]
}